{
  "id": "2374849",
  "name": "pake",
  "font_family": "iconfont",
  "css_prefix_text": "icon-",
  "description": "",
  "glyphs": [
    {
      "icon_id": "18609886",
      "name": "电 话",
      "font_class": "dianhua",
      "unicode": "e744",
      "unicode_decimal": 59204
    },
    {
      "icon_id": "12686954",
      "name": "篮球鞋",
      "font_class": "lanqiuxie",
      "unicode": "e69e",
      "unicode_decimal": 59038
    },
    {
      "icon_id": "4789373",
      "name": "更多",
      "font_class": "gengduo",
      "unicode": "e644",
      "unicode_decimal": 58948
    },
    {
      "icon_id": "356478",
      "name": "微博",
      "font_class": "weibo",
      "unicode": "e62f",
      "unicode_decimal": 58927
    },
    {
      "icon_id": "436242",
      "name": "体恤",
      "font_class": "22",
      "unicode": "e616",
      "unicode_decimal": 58902
    },
    {
      "icon_id": "588719",
      "name": "聊天",
      "font_class": "liaotian",
      "unicode": "e6f3",
      "unicode_decimal": 59123
    },
    {
      "icon_id": "796637",
      "name": "运动服饰",
      "font_class": "yundongfushi",
      "unicode": "e643",
      "unicode_decimal": 58947
    },
    {
      "icon_id": "830288",
      "name": "箭头-右",
      "font_class": "jiantouyou",
      "unicode": "e658",
      "unicode_decimal": 58968
    },
    {
      "icon_id": "834040",
      "name": "箭头_左",
      "font_class": "icon_arrow_left",
      "unicode": "e60c",
      "unicode_decimal": 58892
    },
    {
      "icon_id": "983847",
      "name": "11帐篷",
      "font_class": "zhangpeng",
      "unicode": "e62c",
      "unicode_decimal": 58924
    },
    {
      "icon_id": "986226",
      "name": "微信",
      "font_class": "weixin-copy",
      "unicode": "e65b",
      "unicode_decimal": 58971
    },
    {
      "icon_id": "2506479",
      "name": "足球",
      "font_class": "zuqiu",
      "unicode": "ea78",
      "unicode_decimal": 60024
    },
    {
      "icon_id": "4159789",
      "name": "搜索",
      "font_class": "search",
      "unicode": "e63a",
      "unicode_decimal": 58938
    },
    {
      "icon_id": "8765707",
      "name": "卫衣",
      "font_class": "weiyi",
      "unicode": "e605",
      "unicode_decimal": 58885
    },
    {
      "icon_id": "12097488",
      "name": "客服",
      "font_class": "kefu",
      "unicode": "e661",
      "unicode_decimal": 58977
    },
    {
      "icon_id": "12335997",
      "name": "保龄球",
      "font_class": "baolingqiu",
      "unicode": "e618",
      "unicode_decimal": 58904
    },
    {
      "icon_id": "13355646",
      "name": "篮球鞋AJ-01",
      "font_class": "AJ-",
      "unicode": "e629",
      "unicode_decimal": 58921
    },
    {
      "icon_id": "13355655",
      "name": "篮球鞋AJ-07",
      "font_class": "AJ-1",
      "unicode": "e630",
      "unicode_decimal": 58928
    },
    {
      "icon_id": "13548394",
      "name": "特步图标-线性_羽绒服",
      "font_class": "tebutubiao-xianxing_yurongfu",
      "unicode": "e615",
      "unicode_decimal": 58901
    },
    {
      "icon_id": "15916889",
      "name": "箭头-上",
      "font_class": "jiantou-shang",
      "unicode": "e64c",
      "unicode_decimal": 58956
    },
    {
      "icon_id": "18043713",
      "name": "棒球服_2",
      "font_class": "bangqiufu_2",
      "unicode": "e617",
      "unicode_decimal": 58903
    },
    {
      "icon_id": "18878465",
      "name": "杠铃",
      "font_class": "gangling",
      "unicode": "e6bc",
      "unicode_decimal": 59068
    },
    {
      "icon_id": "18878495",
      "name": "篮球框",
      "font_class": "lanqiukuang",
      "unicode": "e6bd",
      "unicode_decimal": 59069
    }
  ]
}
